Metadata-Version: 1.1
Name: rmotr-b8-pyp-g2-jobs-detector
Version: 0.3.1
Summary: rmotr.com Group 2 | Jobs Detector
Home-page: https://github.com/prestonr83/pyp-w3-gw-jobs-detector/
Author: rmotr.com
Author-email: questions@rmotr.com
License: CC BY-SA 4.0 License
Download-URL: https://github.com/prestonr83/pyp-w3-gw-jobs-detector/tarball/0.3
Platform: UNKNOWN
